ragflow_sdk/__init__.py
ragflow_sdk/ragflow.py
ragflow_sdk/modules/__init__.py
ragflow_sdk/modules/agent.py
ragflow_sdk/modules/base.py
ragflow_sdk/modules/chat.py
ragflow_sdk/modules/chunk.py
ragflow_sdk/modules/dataset.py
ragflow_sdk/modules/document.py
ragflow_sdk/modules/session.py
ragflow_sdk-0.23.1.dist-info/METADATA
ragflow_sdk-0.23.1.dist-info/WHEEL
ragflow_sdk-0.23.1.dist-info/top_level.txt
ragflow_sdk-0.23.1.dist-info/RECORD
