Metadata-Version: 2.4
Name: ragflow-sdk
Version: 0.23.1
Summary: Python client sdk of [RAGFlow](https://github.com/infiniflow/ragflow). RAGFlow is an open-source RAG (Retrieval-Augmented Generation) engine based on deep document understanding.
Author-email: Zhichang Yu <yuzhichang@gmail.com>
License: Apache License, Version 2.0
Requires-Python: <3.15,>=3.12
Requires-Dist: requests<3.0.0,>=2.30.0
Requires-Dist: beartype<1.0.0,>=0.20.0
